dataito/__init__.py
dataito/read.py
dataito/save.py
dataito/transform.py
dataito-1.0.2.dist-info/LICENSE.txt
dataito-1.0.2.dist-info/METADATA
dataito-1.0.2.dist-info/WHEEL
dataito-1.0.2.dist-info/top_level.txt
dataito-1.0.2.dist-info/RECORD
