Metadata-Version: 2.1
Name: dataito
Version: 1.0.2
Summary: Python data input (i), transform (t), output (o), a line of code to read / convert a variety of formats of data files
Home-page: https://github.com/ChoiNgai/dataito
Author: CAIWEI
Author-email: caiwei-email@qq.com
License: UNKNOWN
Project-URL: Bug Tracker, https://github.com/ChoiNgai/dataito/issues
Platform: UNKNOWN
Classifier: Programming Language :: Python :: 3
Classifier: License :: OSI Approved :: MIT License
Classifier: Operating System :: OS Independent
Requires-Python: >=3.6
License-File: LICENSE.txt
